[
  {
    "id": "bitcoin-core-29612",
    "org": "Bitcoin Core",
    "repo": "bitcoin/bitcoin",
    "logo": "https://avatars.githubusercontent.com/u/528860",
    "issue_number": 29612,
    "title": "Add test coverage for descriptor wallet migration",
    "url": "https://github.com/bitcoin/bitcoin/issues/29612",
    "languages": ["C++", "Python"],
    "tags": ["testing", "wallet"],
    "date_added": "2025-05-19"
  },
  {
    "id": "lnd-4910",
    "org": "Lightning Network Daemon",
    "repo": "lightningnetwork/lnd",
    "logo": "https://avatars.githubusercontent.com/u/25188005",
    "issue_number": 4910,
    "title": "HTLCs not appearing in forwarding history after restart",
    "url": "https://github.com/lightningnetwork/lnd/issues/4910",
    "languages": ["Go"],
    "tags": ["lightning", "bug"],
    "date_added": "2025-05-19"
  },
  {
    "id": "bdk-1618",
    "org": "Bitcoin Dev Kit",
    "repo": "bitcoindevkit/bdk",
    "logo": "https://avatars.githubusercontent.com/u/62544739",
    "issue_number": 1618,
    "title": "Add regtest examples to CLI documentation",
    "url": "https://github.com/bitcoindevkit/bdk/issues/1618",
    "languages": ["Rust"],
    "tags": ["docs", "cli"],
    "date_added": "2025-05-19"
  },
  {
    "id": "btcpayserver-5812",
    "org": "BTCPay Server",
    "repo": "btcpayserver/btcpayserver",
    "logo": "https://avatars.githubusercontent.com/u/52160240",
    "issue_number": 5812,
    "title": "Improve error messages for failed webhook deliveries",
    "url": "https://github.com/btcpayserver/btcpayserver/issues/5812",
    "languages": ["C#"],
    "tags": ["webhooks", "ux"],
    "date_added": "2025-05-18"
  },
  {
    "id": "cln-6891",
    "org": "Core Lightning",
    "repo": "ElementsProject/lightning",
    "logo": "https://avatars.githubusercontent.com/u/8597475",
    "issue_number": 6891,
    "title": "Add JSON schema validation for plugin manifests",
    "url": "https://github.com/ElementsProject/lightning/issues/6891",
    "languages": ["C", "Python"],
    "tags": ["plugins", "validation"],
    "date_added": "2025-05-17"
  },
  {
    "id": "fedimint-3201",
    "org": "Fedimint",
    "repo": "fedimint/fedimint",
    "logo": "https://avatars.githubusercontent.com/u/93740015",
    "issue_number": 3201,
    "title": "Write integration tests for e-cash backup and restore",
    "url": "https://github.com/fedimint/fedimint/issues/3201",
    "languages": ["Rust"],
    "tags": ["testing", "backup"],
    "date_added": "2025-05-16"
  },
  {
    "id": "electrs-1022",
    "org": "Electrs",
    "repo": "romanz/electrs",
    "logo": "https://avatars.githubusercontent.com/u/1065999",
    "issue_number": 1022,
    "title": "Document compaction configuration options",
    "url": "https://github.com/romanz/electrs/issues/1022",
    "languages": ["Rust"],
    "tags": ["docs", "configuration"],
    "date_added": "2025-05-15"
  },
  {
    "id": "rust-bitcoin-2918",
    "org": "Rust Bitcoin",
    "repo": "rust-bitcoin/rust-bitcoin",
    "logo": "https://avatars.githubusercontent.com/u/50892734",
    "issue_number": 2918,
    "title": "Add serde support for additional script types",
    "url": "https://github.com/rust-bitcoin/rust-bitcoin/issues/2918",
    "languages": ["Rust"],
    "tags": ["serde", "scripting"],
    "date_added": "2025-05-14"
  }
]
